scopeobj.py
Scopeobj-0.2.1.dist-info/LICENSE
Scopeobj-0.2.1.dist-info/METADATA
Scopeobj-0.2.1.dist-info/WHEEL
Scopeobj-0.2.1.dist-info/top_level.txt
Scopeobj-0.2.1.dist-info/RECORD
